codetree/__init__.py
codetree/cli.py
codetree_cli-0.2.2.dist-info/METADATA
codetree_cli-0.2.2.dist-info/WHEEL
codetree_cli-0.2.2.dist-info/entry_points.txt
codetree_cli-0.2.2.dist-info/top_level.txt
codetree_cli-0.2.2.dist-info/RECORD
