Metadata-Version: 2.2
Name: codetree-cli
Version: 0.2.2
Summary: A tool for counting lines of code in a project.
Home-page: https://github.com/rezamardaniDev/codetree.git
Author: Reza Mardani
Author-email: mardanireza30@gmail.com
Classifier: Programming Language :: Python :: 3
Classifier: License :: OSI Approved :: MIT License
Classifier: Operating System :: OS Independent
Requires-Python: >=3.6
Dynamic: author
Dynamic: author-email
Dynamic: classifier
Dynamic: description
Dynamic: description-content-type
Dynamic: home-page
Dynamic: requires-python
Dynamic: summary
